{
  "animals": [
    {
      "id": 1,
      "name": "Decker",
      "breed": "German Shepherd",
      "imgURL": "https://2.bp.blogspot.com/-u28lZcXAU9o/Vac3S9HkkZI/AAAAAAAAjZI/obYgPZrtvQM/s1600/german%2Bshepherd%2Bhd%2Bwallpapers%2B7.jpg"
    },
    {
      "id": 2,
      "name": "Esme",
      "breed": "Pitbull",
      "imgURL": "https://www.alphapaw.com/wp-content/uploads/2021/01/65216239_438364413417055_6761610141087820951_n-1-1.jpg"
    }
  ],
  "customers": [
    {
      "id": 1,
      "name": "Michael Crichton",
      "address": "101 Jurassic Ave"
    },
    {
      "id": 2,
      "name": "Isaac Asimov",
      "address": "203 Android Pl"
    },
    {
      "id": 3,
      "name": "Stephen King",
      "address": "19 Rose Drive"
    }
  ],
  "employees": [
    {
      "id": 1,
      "name": "Joshua Stewart",
      "location": "Nashville North"
    }
  ],
  "locations": [
    {
      "id": 1,
      "name": "Nashville North",
      "address": "8422 Johnson Pike"
    },
    {
      "id": 2,
      "name": "Nashville South",
      "address": "123 Whatever Rd"
    }
  ]
}